sqlwhat/State.py
sqlwhat/__init__.py
sqlwhat/sct_syntax.py
sqlwhat/test_exercise.py
sqlwhat/checks/__init__.py
sqlwhat/checks/check_funcs.py
sqlwhat/checks/has_funcs.py
sqlwhat-3.9.4.dist-info/LICENSE
sqlwhat-3.9.4.dist-info/METADATA
sqlwhat-3.9.4.dist-info/WHEEL
sqlwhat-3.9.4.dist-info/top_level.txt
sqlwhat-3.9.4.dist-info/RECORD
