Metadata-Version: 2.1
Name: sqlwhat
Version: 3.9.4
Summary: Submission correctness tests for SQL
Home-page: https://github.com/datacamp/sqlwhat
Author: Michael Chow, Filip Schouwenaars
Author-email: michael@datacamp.com
Maintainer: Jeroen Hermans
Maintainer-email: content-engineering@datacamp.com
License: UNKNOWN
Platform: UNKNOWN
Classifier: Programming Language :: Python :: 3
Classifier: License :: OSI Approved :: GNU Affero General Public License v3
Classifier: Operating System :: OS Independent
Requires-Dist: protowhat (~=1.13.0)
Requires-Dist: antlr-plsql (~=0.9.1)
Requires-Dist: antlr-tsql (~=0.12.6)
